app/__init__.py
app/config.py
app/exceptions.py
app/llm.py
app/logger.py
app/schema.py
app/agent/__init__.py
app/agent/base.py
app/agent/manus.py
app/agent/planning.py
app/agent/react.py
app/agent/swe.py
app/agent/toolcall.py
app/flow/__init__.py
app/flow/base.py
app/flow/flow_factory.py
app/flow/planning.py
app/prompt/__init__.py
app/prompt/manus.py
app/prompt/planning.py
app/prompt/swe.py
app/prompt/toolcall.py
app/tool/__init__.py
app/tool/base.py
app/tool/bash.py
app/tool/browser_use_tool.py
app/tool/create_chat_completion.py
app/tool/file_saver.py
app/tool/google_search.py
app/tool/planning.py
app/tool/python_execute.py
app/tool/run.py
app/tool/str_replace_editor.py
app/tool/terminate.py
app/tool/tool_collection.py
openmanus-0.1.0.dist-info/LICENSE
openmanus-0.1.0.dist-info/METADATA
openmanus-0.1.0.dist-info/WHEEL
openmanus-0.1.0.dist-info/top_level.txt
openmanus-0.1.0.dist-info/RECORD
