Metadata-Version: 2.2
Name: openmanus
Version: 0.1.0
Summary: Add your description here
Home-page: https://github.com/mannaandpoem/OpenManus
Author: mannaandpoem and OpenManus Team
Author-email: mannaandpoem@gmail.com
Requires-Python: >=3.12
License-File: LICENSE
Dynamic: author
Dynamic: author-email
Dynamic: home-page
Dynamic: requires-python
